pyspark_spl_tools/__init__.py
pyspark_spl_tools/base.py
pyspark_spl_tools/case_sensitivity.py
pyspark_spl_tools/config.py
pyspark_spl_tools/magic.py
pyspark_spl_tools/utils.py
pyspark_spl_tools/commands/__init__.py
pyspark_spl_tools/commands/data_model.py
pyspark_spl_tools/commands/eval.py
pyspark_spl_tools/commands/fill_null.py
pyspark_spl_tools/commands/rename.py
pyspark_spl_tools/commands/search.py
pyspark_spl_tools/commands/spath.py
pyspark_spl_tools/commands/stats.py
pyspark_spl_tools/commands/tstats.py
pyspark_spl_tools/functions/__init__.py
pyspark_spl_tools/functions/eval.py
pyspark_spl_tools/functions/stats.py
pyspark_spl_tools/functions/utils.py
pyspark_spl_tools/monkeypatches/__init__.py
pyspark_spl_tools/udfs/__init__.py
pyspark_spl_tools-0.3.0.dist-info/licenses/LICENSE
pyspark_spl_tools-0.3.0.dist-info/WHEEL
pyspark_spl_tools-0.3.0.dist-info/METADATA
pyspark_spl_tools-0.3.0.dist-info/RECORD
